steamcmd_wrapper/__init__.py
steamcmd_wrapper/config.py
steamcmd_wrapper/steam_client/__init__.py
steamcmd_wrapper/steam_client/protocol_steamcmd_client.py
steamcmd_wrapper/steam_client/steamcmd_client.py
steamcmd_wrapper/steam_downloader/__init__.py
steamcmd_wrapper/steam_downloader/downloader_requests.py
steamcmd_wrapper/steam_downloader/file_system.py
steamcmd_wrapper/steam_downloader/linux_steamcmd_downloader.py
steamcmd_wrapper/steam_downloader/protocol_steamcmd_downloader.py
steamcmd_wrapper/steam_subprocess/__init__.py
steamcmd_wrapper/steam_subprocess/linux_steam_subprocess.py
steamcmd_wrapper/steam_subprocess/protocol_subprocess.py
steamcmd_wrapper/tests/__init__.py
steamcmd_wrapper/tests/uts/__init__.py
steamcmd_wrapper/tests/uts/steamcmd_client/__init__.py
steamcmd_wrapper/tests/uts/steamcmd_client/test_steamcmd_client.py
steamcmd_wrapper/tests/uts/steamcmd_downloader/__init__.py
steamcmd_wrapper/tests/uts/steamcmd_downloader/test_download_requester.py
steamcmd_wrapper/tests/uts/steamcmd_downloader/test_file_system.py
steamcmd_wrapper/tests/uts/steamcmd_downloader/test_steamcmd_downloader.py
steamcmd_wrapper/tests/uts/steamcmd_subprocess/__init__.py
steamcmd_wrapper/tests/uts/steamcmd_subprocess/echo.py
steamcmd_wrapper/tests/uts/steamcmd_subprocess/test_steam_subprocess.py
Py_SteamCMD_Subprocess_Wrapper-0.1.0.dist-info/LICENSE.md
Py_SteamCMD_Subprocess_Wrapper-0.1.0.dist-info/METADATA
Py_SteamCMD_Subprocess_Wrapper-0.1.0.dist-info/WHEEL
Py_SteamCMD_Subprocess_Wrapper-0.1.0.dist-info/top_level.txt
Py_SteamCMD_Subprocess_Wrapper-0.1.0.dist-info/RECORD
