Metadata-Version: 2.1
Name: Py-SteamCMD-Subprocess-Wrapper
Version: 0.1.0
Summary: SteamCMD Python wrapper to persist steam's login sessions
Author-email: Wojciech Maziarz <wmaziarzw@gmail.com>
Project-URL: Repository, https://github.com/Wojtini/Interactive-SteamCMD-Wrapper
Project-URL: Issues, https://github.com/Wojtini/Interactive-SteamCMD-Wrapper/issues
Keywords: Steam,Steam Server,SteamCMD,Linux
Classifier: Development Status :: 4 - Beta
Classifier: Intended Audience :: Developers
Classifier: Programming Language :: Python :: 3.12
Classifier: Programming Language :: Python :: 3.11
Classifier: Programming Language :: Python :: 3.10
Classifier: Programming Language :: Python :: 3.9
Classifier: Programming Language :: Python :: 3.8
Requires-Python: >=3.8
License-File: LICENSE.md
Requires-Dist: requests >2.0.0
Provides-Extra: dev
Requires-Dist: mypy ; extra == 'dev'
Requires-Dist: pip-tools ; extra == 'dev'
Requires-Dist: ruff ; extra == 'dev'
Requires-Dist: pytest ; extra == 'dev'
Requires-Dist: pyfakefs ; extra == 'dev'
Requires-Dist: requests-mock ; extra == 'dev'
Requires-Dist: types-requests ; extra == 'dev'
